iciba/__init__.py
iciba/__main__.py
iciba-0.1.2.dist-info/METADATA
iciba-0.1.2.dist-info/WHEEL
iciba-0.1.2.dist-info/entry_points.txt
iciba-0.1.2.dist-info/RECORD
